{
  "nodes": [
    {
      "id": "c_users_nicks_octogent_skills_skills_catalog_twitter_reader_scripts_fetch_tweet_py",
      "label": "fetch_tweet.py",
      "file_type": "code",
      "source_file": "skills-catalog/twitter-reader/scripts/fetch_tweet.py",
      "source_location": "L1"
    },
    {
      "id": "scripts_fetch_tweet_fetch_tweet",
      "label": "fetch_tweet()",
      "file_type": "code",
      "source_file": "skills-catalog/twitter-reader/scripts/fetch_tweet.py",
      "source_location": "L22"
    },
    {
      "id": "scripts_fetch_tweet_rationale_23",
      "label": "Fetch tweet content using jina.ai API via curl.",
      "file_type": "rationale",
      "source_file": "skills-catalog/twitter-reader/scripts/fetch_tweet.py",
      "source_location": "L23"
    }
  ],
  "edges": [
    {
      "source": "c_users_nicks_octogent_skills_skills_catalog_twitter_reader_scripts_fetch_tweet_py",
      "target": "sys",
      "relation": "imports",
      "context": "import",
      "confidence": "EXTRACTED",
      "source_file": "skills-catalog/twitter-reader/scripts/fetch_tweet.py",
      "source_location": "L15",
      "weight": 1.0
    },
    {
      "source": "c_users_nicks_octogent_skills_skills_catalog_twitter_reader_scripts_fetch_tweet_py",
      "target": "os",
      "relation": "imports",
      "context": "import",
      "confidence": "EXTRACTED",
      "source_file": "skills-catalog/twitter-reader/scripts/fetch_tweet.py",
      "source_location": "L16",
      "weight": 1.0
    },
    {
      "source": "c_users_nicks_octogent_skills_skills_catalog_twitter_reader_scripts_fetch_tweet_py",
      "target": "argparse",
      "relation": "imports",
      "context": "import",
      "confidence": "EXTRACTED",
      "source_file": "skills-catalog/twitter-reader/scripts/fetch_tweet.py",
      "source_location": "L17",
      "weight": 1.0
    },
    {
      "source": "c_users_nicks_octogent_skills_skills_catalog_twitter_reader_scripts_fetch_tweet_py",
      "target": "subprocess",
      "relation": "imports",
      "context": "import",
      "confidence": "EXTRACTED",
      "source_file": "skills-catalog/twitter-reader/scripts/fetch_tweet.py",
      "source_location": "L18",
      "weight": 1.0
    },
    {
      "source": "c_users_nicks_octogent_skills_skills_catalog_twitter_reader_scripts_fetch_tweet_py",
      "target": "pathlib",
      "relation": "imports_from",
      "context": "import",
      "confidence": "EXTRACTED",
      "source_file": "skills-catalog/twitter-reader/scripts/fetch_tweet.py",
      "source_location": "L19",
      "weight": 1.0
    },
    {
      "source": "c_users_nicks_octogent_skills_skills_catalog_twitter_reader_scripts_fetch_tweet_py",
      "target": "scripts_fetch_tweet_fetch_tweet",
      "relation": "contains",
      "confidence": "EXTRACTED",
      "source_file": "skills-catalog/twitter-reader/scripts/fetch_tweet.py",
      "source_location": "L22",
      "weight": 1.0
    },
    {
      "source": "scripts_fetch_tweet_rationale_23",
      "target": "scripts_fetch_tweet_fetch_tweet",
      "relation": "rationale_for",
      "confidence": "EXTRACTED",
      "source_file": "skills-catalog/twitter-reader/scripts/fetch_tweet.py",
      "source_location": "L23",
      "weight": 1.0
    }
  ],
  "raw_calls": [
    {
      "caller_nid": "scripts_fetch_tweet_fetch_tweet",
      "callee": "getenv",
      "is_member_call": true,
      "source_file": "C:\\Users\\nicks\\octogent-skills\\skills-catalog\\twitter-reader\\scripts\\fetch_tweet.py",
      "source_location": "L24",
      "receiver": null
    },
    {
      "caller_nid": "scripts_fetch_tweet_fetch_tweet",
      "callee": "exit",
      "is_member_call": true,
      "source_file": "C:\\Users\\nicks\\octogent-skills\\skills-catalog\\twitter-reader\\scripts\\fetch_tweet.py",
      "source_location": "L29",
      "receiver": null
    },
    {
      "caller_nid": "scripts_fetch_tweet_fetch_tweet",
      "callee": "run",
      "is_member_call": true,
      "source_file": "C:\\Users\\nicks\\octogent-skills\\skills-catalog\\twitter-reader\\scripts\\fetch_tweet.py",
      "source_location": "L38",
      "receiver": null
    },
    {
      "caller_nid": "scripts_fetch_tweet_fetch_tweet",
      "callee": "exit",
      "is_member_call": true,
      "source_file": "C:\\Users\\nicks\\octogent-skills\\skills-catalog\\twitter-reader\\scripts\\fetch_tweet.py",
      "source_location": "L42",
      "receiver": null
    },
    {
      "caller_nid": "scripts_fetch_tweet_fetch_tweet",
      "callee": "write_text",
      "is_member_call": true,
      "source_file": "C:\\Users\\nicks\\octogent-skills\\skills-catalog\\twitter-reader\\scripts\\fetch_tweet.py",
      "source_location": "L47",
      "receiver": null
    },
    {
      "caller_nid": "scripts_fetch_tweet_fetch_tweet",
      "callee": "Path",
      "is_member_call": false,
      "source_file": "C:\\Users\\nicks\\octogent-skills\\skills-catalog\\twitter-reader\\scripts\\fetch_tweet.py",
      "source_location": "L47",
      "receiver": null
    }
  ]
}
